disba/__about__.py
disba/__init__.py
disba/_base.py
disba/_common.py
disba/_dispersion.py
disba/_eigen.py
disba/_ellipticity.py
disba/_exception.py
disba/_helpers.py
disba/_sensitivity.py
disba/_velocity_model.py
disba/_cps/__init__.py
disba/_cps/_common.py
disba/_cps/_srfker96.py
disba/_cps/_surf96.py
disba/_cps/_swegn96.py
disba-0.7.0.dist-info/LICENSE
disba-0.7.0.dist-info/METADATA
disba-0.7.0.dist-info/WHEEL
disba-0.7.0.dist-info/top_level.txt
disba-0.7.0.dist-info/RECORD
