Metadata-Version: 2.1
Name: disba
Version: 0.7.0
Summary: Numba-accelerated computation of surface wave dispersion
Home-page: https://github.com/keurfonluu/disba
Author: Keurfon Luu
License: BSD 3-Clause License
Project-URL: Code, https://github.com/keurfonluu/disba
Project-URL: Issues, https://github.com/keurfonluu/disba/issues
Platform: any
Classifier: License :: OSI Approved :: BSD License
Classifier: Operating System :: OS Independent
Classifier: Development Status :: 4 - Beta
Classifier: Programming Language :: Python :: 3.8
Classifier: Programming Language :: Python :: 3.9
Classifier: Programming Language :: Python :: 3.10
Classifier: Programming Language :: Python :: 3.11
Classifier: Programming Language :: Python :: 3.12
Requires-Python: >=3.6
License-File: LICENSE
Requires-Dist: importlib_metadata
Requires-Dist: matplotlib
Requires-Dist: numpy
Requires-Dist: numba
